LICENSE
MANIFEST.in
README.md
setup.py
simple_screen/__init__.py
simple_screen/attributes.py
simple_screen/colors.py
simple_screen/entities.py
simple_screen/funcs.py
simple_screen/keys.py
simple_screen.egg-info/PKG-INFO
simple_screen.egg-info/SOURCES.txt
simple_screen.egg-info/dependency_links.txt
simple_screen.egg-info/top_level.txt