Metadata-Version: 2.1
Name: simple_screen
Version: 0.1.17
Summary: Ease of managing color and positioning prints and supplies for teaching purposes.
Home-page: https://github.com/digestiveThinking/simple_screen
Author: Mon Maldonado
Author-email: monterdi@gmail.com
Classifier: Programming Language :: Python :: 3
Classifier: License :: OSI Approved :: MIT License
Classifier: Operating System :: OS Independent
Requires-Python: >=3.6
License-File: LICENSE
